questra/Client.py
questra/__init__.py
questra/objects.py
questra/settings.py
questra-0.5.dist-info/METADATA
questra-0.5.dist-info/WHEEL
questra-0.5.dist-info/top_level.txt
questra-0.5.dist-info/RECORD
