Metadata-Version: 2.4
Name: questra
Version: 0.5
Summary: Search is a powerful library for convenient searching.
Author: Siri_Lv
Author-email: siriteamrs@gmail.com
Keywords: search,google,bing,translation,image-search,image
Classifier: Programming Language :: Python :: 3
Classifier: License :: OSI Approved :: MIT License
Classifier: Operating System :: OS Independent
Requires-Python: >=3.8
Requires-Dist: cloudscraper
Requires-Dist: httpx
Requires-Dist: bs4
Requires-Dist: fake-useragent
Dynamic: author
Dynamic: classifier
Dynamic: description
Dynamic: description-content-type
Dynamic: keywords
Dynamic: requires-dist
Dynamic: requires-python
Dynamic: summary
